patois_stop_words/__init__.py
patois_stop_words/words.txt
patois_stop_words-0.0.1.dist-info/DESCRIPTION.rst
patois_stop_words-0.0.1.dist-info/METADATA
patois_stop_words-0.0.1.dist-info/RECORD
patois_stop_words-0.0.1.dist-info/WHEEL
patois_stop_words-0.0.1.dist-info/metadata.json
patois_stop_words-0.0.1.dist-info/top_level.txt
