Metadata-Version: 2.0
Name: patois-stop-words
Version: 0.0.1
Summary: A list of patois stop words.
Home-page: https://github.com/ANich/patois-stop-words
Author: Alexander Nicholson
Author-email: alexj.nich@hotmail.com
License: MIT
Keywords: patois
Platform: UNKNOWN
Classifier: Intended Audience :: Developers
Classifier: Programming Language :: Python :: 3
